hashily/__init__.py
hashily/ciphers.py
hashily/encoding.py
hashily/transform.py
utils/__init__.py
utils/constants.py
utils/exceptions.py
hashily-0.0.6.dist-info/LICENSE
hashily-0.0.6.dist-info/METADATA
hashily-0.0.6.dist-info/WHEEL
hashily-0.0.6.dist-info/top_level.txt
hashily-0.0.6.dist-info/RECORD
