Metadata-Version: 2.1
Name: hashily
Version: 0.0.6
Summary: A module that allows you to encode and decode text in numerous ciphers.
Home-page: https://github.com/TrueMyst/hashily
Author: myst.67
License: MIT
Project-URL: Issue tracker, https://github.com/TrueMyst/hashily/issues
Project-URL: Documentation, https://hashily.readthedocs.io/en/latest/
Keywords: encryption,utils,encode,ciphers,decode
Platform: UNKNOWN
Classifier: Development Status :: 5 - Production/Stable
Classifier: Intended Audience :: Developers
Classifier: Operating System :: OS Independent
Classifier: License :: OSI Approved :: MIT License
Classifier: Natural Language :: English
Classifier: Programming Language :: Python :: 3
License-File: LICENSE
